lygui/__init__.py
lygui/core.py
lygui/outputs/framedump.py
lygui/outputs/preview.py
lygui/outputs/viewer_http.py
lygui/renderers/software.py
lygui/renderers/text.py
lygui/utils/__init__.py
lygui/utils/color.py
lygui-0.1.0b2.post1.dist-info/licenses/LICENSE
lygui-0.1.0b2.post1.dist-info/METADATA
lygui-0.1.0b2.post1.dist-info/WHEEL
lygui-0.1.0b2.post1.dist-info/top_level.txt
lygui-0.1.0b2.post1.dist-info/RECORD
