Metadata-Version: 2.4
Name: LyGui
Version: 0.1.0b2.post1
Summary: LyGui (beta): zero-deps, pure-Python immediate-mode GUI with a software renderer.
Author: DeathAmir
License: MIT
Keywords: gui,immediate,lygui,software renderer,zero deps
Classifier: Programming Language :: Python :: 3
Classifier: License :: OSI Approved :: MIT License
Classifier: Development Status :: 4 - Beta
Classifier: Operating System :: OS Independent
Requires-Python: >=3.9
License-File: LICENSE
Dynamic: license-file
